misspy/MiWeb.py
misspy/__init__.py
misspy/auth.py
misspy/channels.py
misspy/client.py
misspy/clips.py
misspy/core/__init__.py
misspy/core/exception.py
misspy/core/http.py
misspy/core/ws.py
misspy/data.py
misspy/drive.py
misspy/ext/MiAuth.py
misspy/ext/__init__.py
misspy/ext/admin/__init__.py
misspy/ext/admin/ad.py
misspy/ext/admin/admin.py
misspy/ext/admin/raw.txt
misspy/ext/commands/__init__.py
misspy/ext/commands/bot.py
misspy/ext/commands/hook.py
misspy/ext/commands/ws.py
misspy/federation.py
misspy/hashtags.py
misspy/hook.py
misspy/log.py
misspy/not_recommended.py
misspy/notes.py
misspy/pages.py
misspy/permissions.py
misspy/reaction.py
misspy/server.py
misspy/types.py
misspy/user.py
misspy/util.py
misspy-2024.4.1.dist-info/LICENSE
misspy-2024.4.1.dist-info/METADATA
misspy-2024.4.1.dist-info/WHEEL
misspy-2024.4.1.dist-info/RECORD
