Metadata-Version: 2.1
Name: misspy
Version: 2024.4.1
Summary: High-performance Misskey API framework
Home-page: https://misspy.xyz/
Keywords: misskey,misskey-api,misskey-bot
Author: sonyakun
Author-email: contact@sonyakun.xyz
Requires-Python: >=3.8,<4.0
Classifier: License :: OSI Approved :: MIT License
Classifier: Programming Language :: Python
Classifier: Programming Language :: Python :: 3
Classifier: Programming Language :: Python :: 3.8
Classifier: Programming Language :: Python :: 3.9
Classifier: Programming Language :: Python :: 3.10
Classifier: Programming Language :: Python :: 3.11
Classifier: Programming Language :: Python :: 3.12
Classifier: Programming Language :: Python :: 3 :: Only
Classifier: Topic :: Software Development :: Libraries :: Python Modules
Provides-Extra: dev
Provides-Extra: mkdocs
Provides-Extra: speed
Requires-Dist: aiodns (>=3.1.1,<4.0.0)
Requires-Dist: aiohttp (>=3.9.0,<4.0.0)
Requires-Dist: attrdictionary (>=1.0.0,<2.0.0)
Requires-Dist: charset-normalizer (>=3.3.1,<4.0.0) ; extra == "speed"
Requires-Dist: httpx (>=0.25.0,<0.26.0)
Requires-Dist: mkdocs ; extra == "mkdocs"
Requires-Dist: mkdocs-awesome-pages-plugin ; extra == "mkdocs"
Requires-Dist: mkdocs-git-revision-date-localized-plugin ; extra == "mkdocs"
Requires-Dist: mkdocs-material ; extra == "mkdocs"
Requires-Dist: mkdocstrings ; extra == "mkdocs"
Requires-Dist: mkdocstrings-python ; extra == "mkdocs"
Requires-Dist: orjson (==3.9.15) ; (sys_platform == "windows") and (extra == "speed")
Requires-Dist: orjson (>=3.9.15,<4.0.0) ; (sys_platform == "darwin") and (extra == "speed")
Requires-Dist: orjson (>=3.9.15,<4.0.0) ; (sys_platform == "linux") and (extra == "speed")
Requires-Dist: poethepoet (>=0.22.1,<0.26.0) ; extra == "dev"
Requires-Dist: requests (>=2.31.0,<3.0.0)
Requires-Dist: websockets (>=11.0.3,<13.0.0)
Project-URL: Changelog, https://misspy.xyz/History/
Project-URL: Documentation, https://docs.misspy.xyz/
Project-URL: Repository, https://github.com/misspy-development/misspy
